grammarchecking2/__init__.py
grammarchecking2/app.py
grammarchecking2/static/script.js
grammarchecking2/static/style.css
grammarchecking2/templates/index.html
grammarchecking2-0.1.0.dist-info/METADATA
grammarchecking2-0.1.0.dist-info/WHEEL
grammarchecking2-0.1.0.dist-info/top_level.txt
grammarchecking2-0.1.0.dist-info/RECORD
